MANIFEST.in
README.rst
build_trouble_shooting.md
setup.cfg
setup.py
ant_xgboost.egg-info/PKG-INFO
ant_xgboost.egg-info/SOURCES.txt
ant_xgboost.egg-info/dependency_links.txt
ant_xgboost.egg-info/not-zip-safe
ant_xgboost.egg-info/requires.txt
ant_xgboost.egg-info/top_level.txt
xgboost/Makefile
xgboost/VERSION
xgboost/__init__.py
xgboost/automl_core.py
xgboost/build-python.sh
xgboost/callback.py
xgboost/compat.py
xgboost/core.py
xgboost/libpath.py
xgboost/plotting.py
xgboost/rabit.py
xgboost/sklearn.py
xgboost/training.py
xgboost/build/learner.d
xgboost/build/logging.d
xgboost/build/c_api/c_api.d
xgboost/build/c_api/c_api_error.d
xgboost/build/common/common.d
xgboost/build/common/hist_util.d
xgboost/build/common/host_device_vector.d
xgboost/build/data/data.d
xgboost/build/data/simple_csr_source.d
xgboost/build/data/simple_dmatrix.d
xgboost/build/data/sparse_page_dmatrix.d
xgboost/build/data/sparse_page_raw_format.d
xgboost/build/data/sparse_page_source.d
xgboost/build/data/sparse_page_writer.d
xgboost/build/gbm/gblinear.d
xgboost/build/gbm/gbm.d
xgboost/build/gbm/gbtree.d
xgboost/build/linear/linear_updater.d
xgboost/build/linear/updater_coordinate.d
xgboost/build/linear/updater_shotgun.d
xgboost/build/metric/elementwise_metric.d
xgboost/build/metric/metric.d
xgboost/build/metric/multiclass_metric.d
xgboost/build/metric/rank_metric.d
xgboost/build/objective/hinge.d
xgboost/build/objective/multiclass_obj.d
xgboost/build/objective/objective.d
xgboost/build/objective/rank_obj.d
xgboost/build/objective/regression_obj.d
xgboost/build/predictor/cpu_predictor.d
xgboost/build/predictor/predictor.d
xgboost/build/tree/split_evaluator.d
xgboost/build/tree/tree_model.d
xgboost/build/tree/tree_updater.d
xgboost/build/tree/updater_colmaker.d
xgboost/build/tree/updater_histmaker.d
xgboost/build/tree/updater_prune.d
xgboost/build/tree/updater_quantile_hist.d
xgboost/build/tree/updater_refresh.d
xgboost/build/tree/updater_skmaker.d
xgboost/build/tree/updater_sync.d
xgboost/dmlc-core/.editorconfig
xgboost/dmlc-core/.git
xgboost/dmlc-core/.gitignore
xgboost/dmlc-core/.travis.yml
xgboost/dmlc-core/CMakeLists.txt
xgboost/dmlc-core/LICENSE
xgboost/dmlc-core/Makefile
xgboost/dmlc-core/README.md
