Metadata-Version: 1.1
Name: ant-xgboost
Version: 0.91
Summary: XGBoost Python Package
Home-page: https://github.com/alipay/ant-xgboost
Author: Xu Xiao
Author-email: lovedreamf@gmail.com
License: Apache-2.0
Platform: UNKNOWN
Classifier: License :: OSI Approved :: Apache Software License
Classifier: Development Status :: 5 - Production/Stable
Classifier: Operating System :: OS Independent
Classifier: Programming Language :: Python
Classifier: Programming Language :: Python :: 3
Classifier: Programming Language :: Python :: 3.5
Classifier: Programming Language :: Python :: 3.6
Classifier: Programming Language :: Python :: 3.7
